{"stat.drop.minecraft.stone_pickaxe":1,"stat.pickup.minecraft.bone":3,"stat.leaveGame":1,"stat.mineBlock.minecraft.cobblestone":5,"stat.craftItem.spartanweaponry.greatsword_stone":1,"stat.swimOneCm":3894,"stat.pickup.quark.glass_shards":5,"stat.mineBlock.quark.roots":5,"stat.useItem.minecraft.stone_slab2":7,"stat.pickup.minecraft.bow":1,"stat.pickup.minecraft.rotten_flesh":6,"stat.pickup.minecraft.sand":24,"stat.craftItem.minecraft.furnace":4,"stat.craftItem.minecraft.stone_axe":2,"stat.useItem.nocubessrparmory.twisteddagger":31,"stat.useItem.sparkshammers.hammer_iron":527,"stat.useItem.sparkshammers.hammer_wood":33,"stat.craftItem.spartanweaponry.boomerang_stone":1,"stat.craftItem.minecraft.stone_pickaxe":1,"stat.craftItem.minecraft.cooked_beef":42,"stat.pickup.minecraft.cobblestone":609,"stat.useItem.spartanweaponry.boomerang_stone":4,"stat.flyOneCm":64421,"stat.craftItem.minecraft.iron_shovel":1,"stat.mineBlock.minecraft.sand":24,"stat.useItem.minecraft.cooked_beef":12,"stat.mineBlock.minecraft.iron_ore":68,"stat.timeSinceDeath":37383,"stat.craftItem.spartanshields.shield_basic_wood":1,"stat.useItem.minecraft.iron_pickaxe":22,"stat.pickup.minecraft.stained_hardened_clay":4,"stat.craftItem.minecraft.wooden_pickaxe":1,"stat.useItem.minecraft.iron_shovel":24,"stat.furnaceInteraction":78,"stat.craftItem.spartanweaponry.material":1,"stat.mineBlock.minecraft.coal_ore":183,"stat.pickup.srparasites.lurecomponent1":11,"stat.killEntity.Creeper":2,"stat.pickup.minecraft.string":6,"stat.pickup.minecraft.beef":10,"stat.pickup.minecraft.furnace":9,"stat.craftItem.minecraft.stone_slab2":0,"stat.killEntity.Squid":3,"stat.mineBlock.sparkshammers.hammer_craft":1,"stat.mineBlock.minecraft.stained_hardened_clay":4,"stat.sprintOneCm":94305,"stat.craftItem.minecraft.stick":72,"stat.craftItem.minecraft.wooden_axe":1,"stat.craftItem.minecraft.stone":4,"stat.mineBlock.minecraft.crafting_table":2,"stat.drop":3,"stat.playOneMinute":37383,"stat.craftItem.spartanshields.shield_basic_stone":1,"stat.craftItem.minecraft.iron_pickaxe":1,"stat.craftItem.sparkshammers.hammer_head_wood":2,"stat.killEntity.Zombie":10,"stat.mineBlock.minecraft.gold_ore":10,"stat.mineBlock.minecraft.tallgrass":8,"stat.diveOneCm":5616,"stat.pickup.minecraft.arrow":3,"stat.useItem.minecraft.apple":1,"stat.craftItem.travelersbackpack.backpack_tank":2,"stat.jump":650,"stat.pickup.minecraft.coal":233,"stat.fallOneCm":13731,"stat.useItem.minecraft.stone_axe":59,"stat.pickup.minecraft.gunpowder":2,"stat.crouchOneCm":3319,"stat.pickup.minecraft.spider_eye":1,"stat.craftItem.minecraft.iron_ingot":35,"stat.pickup.minecraft.dirt":8,"stat.craftItem.nocubessrparmory.twistedpart":2,"stat.craftingTableInteraction":25,"stat.pickup.minecraft.iron_ore":79,"stat.craftItem.nocubessrparmory.twisteddagger":1,"stat.pickup.minecraft.gold_ore":16,"stat.mineBlock.minecraft.lapis_ore":2,"stat.pickup.minecraft.leather":3,"stat.damageTaken":953,"stat.mineBlock.minecraft.furnace":9,"stat.useItem.minecraft.wooden_pickaxe":3,"stat.useItem.minecraft.furnace":5,"stat.useItem.spartanweaponry.greatsword_stone":42,"stat.pickup.srparasites.assimilated_flesh":2,"stat.mineBlock.biomesoplenty.plant_0":3,"stat.pickup.minecraft.dye":17,"stat.pickup.minecraft.planks":136,"stat.useItem.sparkshammers.hammer_stone":329,"stat.pickup.minecraft.wheat_seeds":3,"stat.mineBlock.biomesoplenty.gem_ore":1,"stat.useItem.minecraft.stone_pickaxe":16,"stat.craftItem.sparkshammers.hammer_wood":2,"stat.mineBlock.minecraft.glass":2,"stat.craftItem.minecraft.iron_leggings":1,"stat.damageDealt":5194,"stat.craftItem.minecraft.glass":20,"stat.killEntity.Cow":2,"stat.mineBlock.minecraft.dirt":9,"stat.useItem.minecraft.crafting_table":1,"stat.pickup.biomesoplenty.persimmon":1,"stat.walkOneCm":49036,"stat.drop.sparkshammers.hammer_stone":1,"stat.pickup.minecraft.crafting_table":3,"stat.useItem.minecraft.cobblestone":251,"stat.craftItem.minecraft.crafting_table":8,"stat.pickup.biomesoplenty.sapling_1":10,"stat.pickup.sparkshammers.hammer_craft":1,"stat.mineBlock.quark.stone_speleothem":2,"stat.pickup.minecraft.log":122,"stat.pickup.quark.root_flower":1,"stat.craftItem.minecraft.gold_ingot":1,"stat.craftItem.minecraft.iron_chestplate":1,"stat.pickup.minecraft.sapling":23,"stat.pickup.minecraft.apple":2,"stat.pickup.minecraft.ladder":2,"stat.pickup.minecraft.cooked_beef":2,"stat.killEntity.Skeleton":4,"stat.craftItem.sparkshammers.hammer_craft":1,"stat.pickup.biomesoplenty.gem":1,"stat.craftItem.minecraft.planks":88,"stat.killEntity.Spider":4,"stat.mobKills":38,"stat.pickup.minecraft.book":9,"stat.mineBlock.minecraft.log":139,"stat.mineBlock.minecraft.bookshelf":3,"stat.mineBlock.minecraft.leaves":5,"stat.sneakTime":1528,"stat.drop.minecraft.stone_axe":1,"stat.useItem.minecraft.wooden_axe":2,"stat.mineBlock.minecraft.stone":641}